LICENSE.rst
README.md
setup.cfg
setup.py
src/flake_type_annotations_plugin.py
src/flake_type_annotations_plugin.egg-info/PKG-INFO
src/flake_type_annotations_plugin.egg-info/SOURCES.txt
src/flake_type_annotations_plugin.egg-info/dependency_links.txt
src/flake_type_annotations_plugin.egg-info/entry_points.txt
src/flake_type_annotations_plugin.egg-info/requires.txt
src/flake_type_annotations_plugin.egg-info/top_level.txt