Metadata-Version: 2.1
Name: flake-type-annotations-plugin
Version: 0.0.1
Summary: flake8 plugin for type annotations
Home-page: https://github.com/waszker/flake-type-annotations-plugin
Author: Piotr Waszkiewicz
Author-email: waszka23@gmail.com
License: MIT
Project-URL: Bug Reports, https://github.com/waszker/flake-type-annotations-plugin/issues
Project-URL: Source, https://github.com/waszker/flake-type-annotations-plugin
Keywords: python,flake8,type annotations
Classifier: Framework :: Flake8
Classifier: Environment :: Console
Classifier: Intended Audience :: Developers
Classifier: License :: OSI Approved :: MIT License
Classifier: Programming Language :: Python :: 3
Classifier: Programming Language :: Python :: 3.7
Classifier: Programming Language :: Python :: 3.8
Classifier: Programming Language :: Python :: 3.9
Classifier: Programming Language :: Python :: 3.10
Classifier: Programming Language :: Python :: 3.11
Classifier: Programming Language :: Python :: 3 :: Only
Classifier: Topic :: Software Development :: Libraries :: Python Modules
Classifier: Topic :: Software Development :: Quality Assurance
Requires-Python: >=3.7, <4
License-File: LICENSE.rst
